{
  "date": "2026-04-11",
  "headline": "Reduce Risk: Today's Security Priorities",
  "digest_items": [
    {
      "type": "tip",
      "title": "Use secure random number generation",
      "why": "Weak randomness compromises cryptographic operations",
      "fix": "Use crypto.randomBytes() or secrets module, not Math.random()"
    },
    {
      "type": "tip",
      "title": "Use security linters in CI/CD",
      "why": "Automated security checks catch vulnerabilities before deployment",
      "fix": "Integrate tools like Bandit (Python), ESLint security plugin (JS)"
    },
    {
      "type": "pattern",
      "title": "Implement data classification",
      "why": "Classification ensures appropriate security controls for sensitive data",
      "fix": "Label data as public, internal, confidential, or restricted"
    },
    {
      "type": "pattern",
      "title": "Implement input validation",
      "why": "Unvalidated input leads to injection attacks and data corruption",
      "fix": "Validate all user input on both client and server side"
    },
    {
      "type": "pattern",
      "title": "Implement zero trust architecture",
      "why": "Zero trust assumes breach and verifies every access request",
      "fix": "Require authentication for all resources regardless of network location"
    }
  ]
}